{
  "id": "rss-20260709-030",
  "title": "Echoes of the AI Winter",
  "source": "rss",
  "source_url": "https://netzhansa.com/echoes-of-the-ai-winter/",
  "author": "",
  "published_at": "2026-07-09T02:52:11Z",
  "collected_at": "2026-07-09T02:52:11Z",
  "summary": "该仓库是一个关于AI寒冬（AI Winter）历史的文章或资源集合，记录了人工智能领域在早期发展过程中经历的挫折、资金削减和研究停滞时期。通过回顾这段历史，它帮助理解AI技术的周期性波动和当前AI热潮的背景。核心功能是提供历史视角和反思，技术亮点在于对AI发展历程的深度分析和警示。",
  "key_insight": "AI寒冬的历史教训提醒我们，当前AI热潮可能面临类似的周期性风险，需谨慎评估技术泡沫。",
  "score": 5,
  "tags": [
    "AI History",
    "AI Winter",
    "Historical Analysis",
    "Tech Cycles"
  ],
  "audience": "intermediate",
  "status": "draft",
  "category": "historical-analysis",
  "updated_at": "2026-07-09T02:52:11Z"
}