{
  "id": "rss-20260521-034",
  "title": "New ways to create and get things done in Google Workspace",
  "source": "rss",
  "source_url": "https://blog.google/products-and-platforms/products/workspace/workspace-updates/",
  "author": "",
  "published_at": "2026-05-21T03:35:47Z",
  "collected_at": "2026-05-21T03:35:47Z",
  "summary": "该仓库介绍了Google Workspace的最新更新，包括Gmail、Docs和Keep中的新语音功能，一个名为Google Pics的新设计工具，以及AI Inbox的更新。这些功能旨在提升用户的生产力和创造力，通过集成AI技术简化工作流程。技术亮点包括语音交互、AI驱动的收件箱管理以及设计工具的创新，展示了Google在办公效率领域的持续创新。",
  "key_insight": "Google Workspace通过语音AI和设计工具扩展了办公自动化边界，但并非纯AI研究项目。",
  "score": 7,
  "tags": [
    "AI",
    "Google Workspace",
    "Voice",
    "Productivity"
  ],
  "audience": "intermediate",
  "status": "draft",
  "category": "productivity-tools",
  "updated_at": "2026-05-21T03:35:47Z"
}